fancy_ctypes-0.2.1.dist-info/licenses/LICENSE
fancytypes/__init__.py
fancytypes/_types.py
fancytypes/ctypes.py
fancytypes/sharedlib.py
fancytypes/types.py
fancy_ctypes-0.2.1.dist-info/METADATA
fancy_ctypes-0.2.1.dist-info/WHEEL
fancy_ctypes-0.2.1.dist-info/top_level.txt
fancy_ctypes-0.2.1.dist-info/RECORD
