Metadata-Version: 2.4
Name: fancy-ctypes
Version: 0.2.1
Summary: Ctypes wrapper for easier Python interoperability with Fortran and C
Author-email: hlatorrec <hlatorre@icm.csic.es>
License:                     GNU GENERAL PUBLIC LICENSE
Project-URL: Homepage, https://github.com/hlatorrec/fancy-ctypes
Project-URL: Bug Tracker, https://github.com/hlatorrec/fancy-ctypes/issues
Keywords: python,c,cpp,fortran,python3,interoperability,ctypes,wrapper,shared,external,library,bindings,binaries
Classifier: Programming Language :: Python :: 3.10
Classifier: Programming Language :: Python :: 3.11
Classifier: Programming Language :: Python :: 3.12
Classifier: Programming Language :: Python :: 3.13
Classifier: Programming Language :: Fortran
Classifier: Programming Language :: C
Classifier: Operating System :: OS Independent
Requires-Python: >=3.10
License-File: LICENSE
Requires-Dist: numpy>=1.23
Dynamic: license-file
